animatplot/animate.py
animatplot/animate3.py
animatplot/init.py
animatplot-0.1.dev3.dist-info/DESCRIPTION.rst
animatplot-0.1.dev3.dist-info/METADATA
animatplot-0.1.dev3.dist-info/RECORD
animatplot-0.1.dev3.dist-info/WHEEL
animatplot-0.1.dev3.dist-info/metadata.json
animatplot-0.1.dev3.dist-info/top_level.txt
