Metadata-Version: 2.0
Name: animatplot
Version: 0.1.dev3
Summary: Making animating in matplotlib easy
Home-page: https://github.com/t-makaro/animatplot/
Author: Tyler Makaro
Author-email: UNKNOWN
License: MIT
Platform: UNKNOWN
Classifier: Development Status :: 3 - Alpha
Classifier: License :: OSI Approved :: MIT License
Classifier: Programming Language :: Python :: 3.6
Requires-Dist: matplotlib
